BioPlate/__init__.py
BioPlate/array.py
BioPlate/bioplate.py
BioPlate/count.py
BioPlate/inserts.py
BioPlate/iterate.py
BioPlate/manipulation.py
BioPlate/matrix.py
BioPlate/plate.py
BioPlate/stack.py
BioPlate/utilitis.py
BioPlate/database/__init__.py
BioPlate/database/database.py
BioPlate/database/plate_db.py
BioPlate/database/plate_historic_db.py
BioPlate/writer/__init__.py
BioPlate/writer/from_excel.py
BioPlate/writer/to_excel.py
BioPlate-0.1.4.dist-info/LICENCE.md
BioPlate-0.1.4.dist-info/METADATA
BioPlate-0.1.4.dist-info/WHEEL
BioPlate-0.1.4.dist-info/top_level.txt
BioPlate-0.1.4.dist-info/RECORD
